avasdk/__init__.py
avasdk/exceptions.py
avasdk/plugins/__init__.py
avasdk/plugins/builders/__init__.py
avasdk/plugins/builders/event.py
avasdk/plugins/builders/request.py
avasdk/plugins/builders/response.py
avasdk/plugins/hasher/__init__.py
avasdk/plugins/log/__init__.py
avasdk/plugins/manifest/__init__.py
avasdk/plugins/model/__init__.py
avasdk/plugins/utils/__init__.py
avasdk-1.0.3.dist-info/DESCRIPTION.rst
avasdk-1.0.3.dist-info/METADATA
avasdk-1.0.3.dist-info/RECORD
avasdk-1.0.3.dist-info/WHEEL
avasdk-1.0.3.dist-info/metadata.json
avasdk-1.0.3.dist-info/top_level.txt
