Metadata-Version: 2.0
Name: avasdk
Version: 1.0.3
Summary: UNKNOWN
Home-page: https://github.com/ava-project
Author: dorianamouroux
Author-email: UNKNOWN
License: Apache
Keywords: ava,sdk
Platform: UNKNOWN
Classifier: Development Status :: 1 - Planning
Classifier: Intended Audience :: Developers
Classifier: License :: OSI Approved :: Apache Software License
Classifier: Programming Language :: Python :: 3
Classifier: Programming Language :: Python :: 3.2
Classifier: Programming Language :: Python :: 3.3
Classifier: Programming Language :: Python :: 3.4
Requires-Dist: valideer
